profile_local/__init__.py
profile_local/comprehensive_profile.py
profile_local/constants_profile_local.py
profile_local/profiles_local.py
profile_local-0.0.95.dist-info/METADATA
profile_local-0.0.95.dist-info/WHEEL
profile_local-0.0.95.dist-info/top_level.txt
profile_local-0.0.95.dist-info/RECORD
