Metadata-Version: 2.4
Name: profile-local
Version: 0.0.95
Summary: This is a package for sharing common crud operation to profile schema in the db
Home-page: https://github.com/circles-zone/profile-local-python-package
Author: Circles
Author-email: info@circlez.ai
Classifier: Programming Language :: Python :: 3
Classifier: License :: Other/Proprietary License
Classifier: Operating System :: OS Independent
Requires-Dist: database-mysql-local>=0.1.46
Requires-Dist: email-address-local>=0.0.40
Requires-Dist: gender-local>=0.0.10
Requires-Dist: group-remote>=0.0.111
Requires-Dist: group-profile-remote>=0.0.29
Requires-Dist: language-remote>=0.0.20
Requires-Dist: location-local>=0.0.103
Requires-Dist: logger-local>=0.0.135
Requires-Dist: operational-hours-local>=0.0.23
Requires-Dist: profile-profile-local>=0.0.18
Requires-Dist: profile-reaction-local>=0.0.17
Requires-Dist: reaction-local>=0.0.17
Requires-Dist: location-profile-local>=0.0.51
Requires-Dist: person-local>=0.0.51
Requires-Dist: user-context-remote>=0.0.75
Requires-Dist: storage-local>=0.1.38
Requires-Dist: python-sdk-remote>=0.0.93
Requires-Dist: visibility-local>=0.0.3
Dynamic: author
Dynamic: author-email
Dynamic: classifier
Dynamic: description
Dynamic: description-content-type
Dynamic: home-page
Dynamic: requires-dist
Dynamic: summary
